minecraft/__init__.py
minecraft/async_mcrcon.py
minecraft/classes.py
minecraft/errors.py
minecraft_crazygmr101-0.1.0.dist-info/LICENSE.md
minecraft_crazygmr101-0.1.0.dist-info/METADATA
minecraft_crazygmr101-0.1.0.dist-info/WHEEL
minecraft_crazygmr101-0.1.0.dist-info/top_level.txt
minecraft_crazygmr101-0.1.0.dist-info/RECORD
