Metadata-Version: 2.1
Name: minecraft-crazygmr101
Version: 0.1.0
Summary: A package letting you interact with a Java Minecraft server through RCON
Home-page: https://github.com/united-minecrafters/minecraft-rcon-client
Author: Daniel Nash
Author-email: dannash987@gmail.com
License: UNKNOWN
Platform: UNKNOWN
Classifier: Programming Language :: Python :: 3
Classifier: License :: OSI Approved :: MIT License
Classifier: Operating System :: OS Independent
Requires-Python: >=3.6
